zest/__init__.py
zest/version.py
zest/zest.py
zest/zest_runner.py
zbs.zest-1.0.9.dist-info/LICENSE
zbs.zest-1.0.9.dist-info/METADATA
zbs.zest-1.0.9.dist-info/WHEEL
zbs.zest-1.0.9.dist-info/entry_points.txt
zbs.zest-1.0.9.dist-info/top_level.txt
zbs.zest-1.0.9.dist-info/RECORD
