Metadata-Version: 2.1
Name: zbs.zest
Version: 1.0.9
Summary: A function-oriented testing framework for Python 3.
Home-page: https://github.com/zsimpson/zbs.zest
Author: Zack Booth Simpson
Author-email: zack.simpson+pypi@gmail.com
License: GPLv3
Platform: UNKNOWN
Classifier: Intended Audience :: Developers
Classifier: License :: OSI Approved :: GNU General Public License v3 (GPLv3)
Classifier: Topic :: Software Development
Classifier: Programming Language :: Python :: 3
Classifier: Programming Language :: Python :: 3.7
Requires-Python: >=3.6
